secbench/storage/__init__.py
secbench/storage/__main__.py
secbench/storage/dataset.py
secbench/storage/store.py
secbench_storage-3.7.1.dist-info/LICENSE
secbench_storage-3.7.1.dist-info/METADATA
secbench_storage-3.7.1.dist-info/WHEEL
secbench_storage-3.7.1.dist-info/entry_points.txt
secbench_storage-3.7.1.dist-info/top_level.txt
secbench_storage-3.7.1.dist-info/RECORD
