Metadata-Version: 2.2
Name: secbench-storage
Version: 3.7.1
Summary: Trace storage format based on HDF5 developped by CEA
Author-email: Secbench team <support@secbench.fr>
License: 
Project-URL: Homepage, https://doc.secbench.fr
Project-URL: Bug Reports, https://github.com/CEA-Leti/secbench/issues
Project-URL: Source, https://github.com/CEA-Leti/secbench
Classifier: Programming Language :: Python :: 3
Classifier: Programming Language :: Python :: 3 :: Only
Classifier: Programming Language :: Python :: 3.9
Classifier: Programming Language :: Python :: 3.10
Classifier: Programming Language :: Python :: 3.11
Classifier: Programming Language :: Python :: 3.12
Classifier: Programming Language :: Python :: 3.13
Classifier: Topic :: Security
Classifier: Topic :: Scientific/Engineering
Classifier: Intended Audience :: Developers
Classifier: Intended Audience :: Science/Research
Classifier: License :: OSI Approved :: CEA CNRS Inria Logiciel Libre License, version 2.1 (CeCILL-2.1)
Requires-Python: >=3.9
License-File: LICENSE
Requires-Dist: numpy>=1.18
Requires-Dist: asciitree>=0.3
Requires-Dist: h5py>=3.6
Requires-Dist: tabulate>=0.9
Requires-Dist: click>=8.0
